nmrxiv_downloader/__init__.py
nmrxiv_downloader/__main__.py
nmrxiv_downloader/cli.py
nmrxiv_downloader/client.py
nmrxiv_downloader/models.py
nmrxiv_downloader/output.py
nmrxiv_downloader-0.1.0.dist-info/METADATA
nmrxiv_downloader-0.1.0.dist-info/WHEEL
nmrxiv_downloader-0.1.0.dist-info/entry_points.txt
nmrxiv_downloader-0.1.0.dist-info/licenses/LICENSE
nmrxiv_downloader-0.1.0.dist-info/RECORD
