Metadata-Version: 2.4
Name: nmrxiv-downloader
Version: 0.1.0
Summary: CLI tool for searching and downloading NMR datasets from nmrxiv.org
Project-URL: Homepage, https://github.com/steinbeck/nmrxiv-downloader
Project-URL: Repository, https://github.com/steinbeck/nmrxiv-downloader.git
Project-URL: Issues, https://github.com/steinbeck/nmrxiv-downloader/issues
Author-email: Christoph Steinbeck <christoph.steinbeck@gmail.com>
License: MIT License
License-File: LICENSE
Keywords: chemistry,cli,natural-products,nmr,nmrxiv,spectroscopy,structure-elucidation
Classifier: Development Status :: 4 - Beta
Classifier: Environment :: Console
Classifier: Intended Audience :: Science/Research
Classifier: License :: OSI Approved :: MIT License
Classifier: Operating System :: OS Independent
Classifier: Programming Language :: Python :: 3
Classifier: Programming Language :: Python :: 3.10
Classifier: Programming Language :: Python :: 3.11
Classifier: Programming Language :: Python :: 3.12
Classifier: Topic :: Scientific/Engineering :: Bio-Informatics
Classifier: Topic :: Scientific/Engineering :: Chemistry
Requires-Python: >=3.10
Requires-Dist: httpx>=0.27.0
Requires-Dist: pydantic>=2.5.0
Requires-Dist: rich>=13.0.0
Requires-Dist: typer>=0.12.0
Provides-Extra: dev
Requires-Dist: pytest>=7.0.0; extra == 'dev'
Requires-Dist: ruff>=0.1.0; extra == 'dev'
